{
  "db": {
    "name": "db",
    "connector": "memory"
  },
  "postgre": {
    "host": "localhost",
    "port": 5432,
    "url": "",
    "database": "rcp_db",
    "password": "1234",
    "name": "postgre",
    "user": "postgres",
    "connector": "postgresql"
  },
  "foremails": {
    "name": "foremails",
    "connector": "mail",
    "transports": [
      {
        "type": "smtp",
        "host": "smtp.gmail.com",
        "secure": true,
        "port": 465,
        "tls": {
          "rejectUnauthorized": false
        },
        "auth": {
          "user": "psemberekajr@gmail.com",
          "pass": "@Wali53mb3@1921"
        }
      }
    ]
  }
}
